<?xml version="1.0"?>
<data>
    <xpath expr="/form" position="replace_attributes">
        <form string="Product"/>
    </xpath>
    <xpath expr="/form/notebook/page[@id='summary']" position="after">
        <page string="Complementary Data" id="complementary_data">
            <field name="complementary_data_def" colspan="4"/>
        </page>
    </xpath>
    <xpath expr="/form/notebook/page[@id='managers']" position="before">
        <page string="Coverages" id="option">
            <field name="coverages"/>
        </page>
    </xpath>
    <xpath expr="/form/notebook/page[@id='admin']/group[@id='left']"
        position="inside">
        <label name="kind"/>
        <field name="kind"/>
        <label name="contract_generator"/>
        <field name="contract_generator"/>
        <newline/>
        <label name="currency"/>
        <field name="currency"/>
        <newline/>
    </xpath>
</data>
