<?xml version="1.0"?>
<!-- This file is part of Coog. The COPYRIGHT file at the top level of
this repository contains the full copyright notices and license terms. -->
<form>
    <label name="covered_person"/>
    <field name="covered_person"/>
    <label name="act_description"/>
    <field name="act_description"/>
    <label name="act_date"/>
    <field name="act_date"/>
    <label name="act_end_date"/>
    <field name="act_end_date"/>
    <label name="quantity"/>
    <field name="quantity"/>
    <label name="total_charges"/>
    <field name="total_charges"/>
    <field name="loss" invisible="1"/>
</form>
