<?xml version="1.0"?>
<!-- This file is part of Coog. The COPYRIGHT file at the top level of
this repository contains the full copyright notices and license terms. -->
<tryton>
    <data>
        <record model="ir.ui.menu-res.group" id="menu_slip_financial_manage">
            <field name="menu" ref="account_invoice_slip.menu_slip"/>
            <field name="group" ref="account_cog.group_financial_manage"/>
        </record>
        <record model="ir.model.access" id="access_invoice_slip_configuration_financial_manage">
            <field name="model" search="[('model', '=', 'account.invoice.slip.configuration')]"/>
            <field name="group" ref="account_cog.group_financial_manage"/>
            <field name="perm_read" eval="True"/>
            <field name="perm_write" eval="True"/>
            <field name="perm_create" eval="True"/>
            <field name="perm_delete" eval="True"/>
        </record>
        <record model="ir.model.access" id="access_invoice_slip_configuration_financial_read">
            <field name="model" search="[('model', '=', 'account.invoice.slip.configuration')]"/>
            <field name="perm_read" eval="True"/>
            <field name="perm_write" eval="False"/>
            <field name="perm_create" eval="False"/>
            <field name="perm_delete" eval="False"/>
        </record>
    </data>
</tryton>
