<?xml version="1.0"?>
<!-- This file is part of Coog. The COPYRIGHT file at the top level of
this repository contains the full copyright notices and license terms. -->
<tryton>
    <data>
        <record model="ir.ui.icon" id="batch_icon">
            <field name="name">batch</field>
            <field name="path">icons/batch.svg</field>
        </record>
        <record model="ir.ui.icon" id="coopengo-close_icon">
            <field name="name">coopengo-close</field>
            <field name="path">icons/coopengo-close.svg</field>
        </record>
        <record model="ir.ui.icon" id="tag_icon">
            <field name="name">tag</field>
            <field name="path">icons/tag.svg</field>
        </record>
        <record model="ir.ui.icon" id="cancel-list_icon">
            <field name="name">cancel-list</field>
            <field name="path">icons/cancel-list.svg</field>
        </record>
        <record model="ir.ui.icon" id="traffic_light_red_icon">
            <field name="name">traffic_light_red</field>
            <field name="path">icons/traffic_light_red.svg</field>
        </record>
        <record model="ir.ui.icon" id="traffic_light_green_icon">
            <field name="name">traffic_light_green</field>
            <field name="path">icons/traffic_light_green.svg</field>
        </record>
        <record model="ir.ui.icon" id="check_icon">
            <field name="name">check</field>
            <field name="path">icons/check.svg</field>
        </record>
        <record model="ir.ui.icon" id="rounded_warning_icon">
            <field name="name">rounded_warning</field>
            <field name="path">icons/rounded_warning.svg</field>
        </record>
        <record model="ir.ui.icon" id="reload_and_check_icon">
            <field name="name">reload_and_check</field>
            <field name="path">icons/reload_and_check.svg</field>
        </record>
        <record model="ir.ui.icon" id="play_icon">
            <field name="name">play</field>
            <field name="path">icons/play.svg</field>
        </record>
        <record model="ir.ui.icon" id="pause_icon">
            <field name="name">pause</field>
            <field name="path">icons/pause.svg</field>
        </record>
        <record model="ir.ui.icon" id="void_icon">
            <field name="name">void</field>
            <field name="path">icons/void.svg</field>
        </record>
        <record model="ir.ui.icon" id="stop_icon">
            <field name="name">stop</field>
            <field name="path">icons/stop.svg</field>
        </record>
        <record model="ir.ui.icon" id="plus_icon">
            <field name="name">plus</field>
            <field name="path">icons/plus.svg</field>
        </record>
        <record model="ir.ui.icon" id="minus_icon">
            <field name="name">minus</field>
            <field name="path">icons/minus.svg</field>
        </record>
        <record model="ir.ui.icon" id="shuffle_icon">
            <field name="name">shuffle</field>
            <field name="path">icons/shuffle.svg</field>
        </record>
        <record model="ir.ui.icon" id="pencil_blue_icon">
            <field name="name">pencil_blue</field>
            <field name="path">icons/pencil-blue.svg</field>
        </record>
        <record model="ir.ui.icon" id="pencil_black_icon">
            <field name="name">pencil_black</field>
            <field name="path">icons/pencil-black.svg</field>
        </record>
    </data>
</tryton>
