<?xml version="1.0"?><tryton>    <data>        <record model="ir.action.act_window" id="act_employee_form">            <field name="name">College</field>            <field name="res_model">party.employee</field>        </record>        <record model="ir.ui.view" id="employee_view_form2">            <field name="model">party.employee</field>            <field name="type">form</field>            <field name="inherit" ref="coop_party.employee_view_form2"/>            <field name="name">employee_form</field>        </record>        <record model="ir.ui.view" id="employee_view_tree">            <field name="model">party.employee</field>            <field name="type">tree</field>            <field name="inherit" ref="coop_party.employee_view_tree"/>            <field name="name">employee_tree</field>        </record>        <record model="ir.action.act_window.view" id="act_employee_form_view1">            <field name="sequence" eval="10"/>            <field name="view" ref="employee_view_tree"/>            <field name="act_window" ref="act_employee_form"/>        </record>        <record model="ir.action.act_window.view" id="act_employee_form_view2">            <field name="sequence" eval="20"/>            <field name="view" ref="employee_view_form2"/>            <field name="act_window" ref="act_employee_form"/>        </record>    </data></tryton>