<?xml version="1.0"?>
<tryton>
    <data group="1">
        <record model="ir.message" id="msg_party_is_on_claim">
            <field name="text">The party %(party)s can not be erased because it is covered on the following open claims:
%(claims)s</field>
        </record>
        <record model="ir.message" id="msg_relapse">
            <field name="text">Relapse</field>
        </record>
        <record model="ir.message" id="msg_previous_loss_end_date_missing">
            <field name="text">The previous std doesn't have an end date defined.</field>
        </record>
        <record model="ir.message" id="msg_one_day_between_relapse_and_previous_loss">
            <field name="text">One day is required between the relapse and the previous std.</field>
        </record>
        <record model="ir.message" id="msg_start_date">
            <field name="text">Start Date:</field>
        </record>
        <record model="ir.message" id="msg_std_start_date">
            <field name="text">STD Start Date:</field>
        </record>
        <record model="ir.message" id="msg_ltd_start_date">
            <field name="text">LTD Start Date:</field>
        </record>
        <record model="ir.message" id="msg_end_date">
            <field name="text">End Date:</field>
        </record>
        <record model="ir.message" id="msg_std_end_date">
            <field name="text">STD End Date:</field>
        </record>
        <record model="ir.message" id="msg_ltd_end_date">
            <field name="text">LTD End Date:</field>
        </record>
        <record model="ir.message" id="msg_missing_relapse_initial_loss">
            <field name="text">The initial loss is missing on the relapse: %(loss)s.</field>
        </record>
        <record model="ir.message" id="msg_multiple_covered_found">
            <field name="text">More than one covered element have been found for the claim %(claim)s at %(date)s for %(rec_name)s.</field>
        </record>
        <record model="ir.message" id="msg_covered_party_enum">
            <field name="text">Covered Party</field>
        </record>
        <record model="ir.message" id="msg_manual_list_enum">
            <field name="text">Manual List</field>
        </record>
        <record model="ir.message" id="msg_loss_date">
            <field name="text">Loss date</field>
        </record>
        <record model="ir.message" id="msg_death_date_invalid">
            <field name="text">Death date of the covered person is not set or not equal to the loss date </field>
        </record>
    </data>
</tryton>
